molieregen/__init__.py
molieregen/cli.py
molieregen/config.py
molieregen/generator.py
molieregen-0.1.2.dist-info/entry_points.txt
molieregen-0.1.2.dist-info/licenses/LICENSE
molieregen-0.1.2.dist-info/WHEEL
molieregen-0.1.2.dist-info/METADATA
molieregen-0.1.2.dist-info/RECORD
