Metadata-Version: 2.4
Name: molieregen
Version: 0.1.2
Summary: Generate invoices and quotes with style.
Author-email: Caribbean Code <caribbeancodelab@gmail.com>
Requires-Python: >=3.8
License-File: LICENSE
Requires-Dist: typer[all]
Requires-Dist: jinja2
Requires-Dist: weasyprint
